{
  "service": "Meshy.ai",
  "runStamp": "20260520T030918Z",
  "sources": [
    {
      "title": "Meshy.ai official site",
      "url": "https://www.meshy.ai/",
      "id": "meshy-ai-official-site-1",
      "fetched_at": "2026-05-20T03:09:18.437Z",
      "fetch_status": "fetched",
      "http_status": 200,
      "final_url": "https://www.meshy.ai/",
      "content_type": "text/html; charset=utf-8",
      "text_chars": 13317
    },
    {
      "title": "Meshy.ai docs",
      "url": "https://docs.meshy.ai/",
      "id": "meshy-ai-docs-2",
      "fetched_at": "2026-05-20T03:09:24.666Z",
      "fetch_status": "fetched",
      "http_status": 200,
      "final_url": "https://docs.meshy.ai/en",
      "content_type": "text/html; charset=utf-8",
      "text_chars": 3147
    },
    {
      "title": "Meshy.ai pricing",
      "url": "https://www.meshy.ai/pricing",
      "id": "meshy-ai-pricing-3",
      "fetched_at": "2026-05-20T03:09:35.635Z",
      "fetch_status": "fetched",
      "http_status": 200,
      "final_url": "https://www.meshy.ai/pricing",
      "content_type": "text/html; charset=utf-8",
      "text_chars": 12760
    },
    {
      "title": "Meshy.ai blog",
      "url": "https://www.meshy.ai/blog",
      "id": "meshy-ai-blog-4",
      "fetched_at": "2026-05-20T03:09:41.947Z",
      "fetch_status": "fetched",
      "http_status": 200,
      "final_url": "https://www.meshy.ai/blog",
      "content_type": "text/html; charset=utf-8",
      "text_chars": 6196
    }
  ]
}